CHANGES.txt
LICENSE.txt
README.txt
TODO.txt
bootstrap.py
buildout.cfg
setup.py
src/tha/__init__.py
src/tha.tagfinder.egg-info/PKG-INFO
src/tha.tagfinder.egg-info/SOURCES.txt
src/tha.tagfinder.egg-info/dependency_links.txt
src/tha.tagfinder.egg-info/entry_points.txt
src/tha.tagfinder.egg-info/namespace_packages.txt
src/tha.tagfinder.egg-info/not-zip-safe
src/tha.tagfinder.egg-info/requires.txt
src/tha.tagfinder.egg-info/top_level.txt
src/tha/tagfinder/USAGE.txt
src/tha/tagfinder/__init__.py
src/tha/tagfinder/extracter.py
src/tha/tagfinder/finder.py
src/tha/tagfinder/lister.py
src/tha/tagfinder/tests/__init__.py
src/tha/tagfinder/tests/extracter.txt
src/tha/tagfinder/tests/finder.txt
src/tha/tagfinder/tests/lister.txt
src/tha/tagfinder/tests/sample.txt
src/tha/tagfinder/tests/test_setup.py
src/tha/tagfinder/tests/fixture/customer/site/tags/something.txt
src/tha/tagfinder/tests/fixture/customer/site/trunk/something.txt
src/tha/tagfinder/tests/fixture/just/some/directory/something.txt
src/tha/tagfinder/tests/fixture/project1/branches/reinout-rendering/something.txt
src/tha/tagfinder/tests/fixture/project1/tags/0.1/something.txt
src/tha/tagfinder/tests/fixture/project1/tags/0.2/something.txt
src/tha/tagfinder/tests/fixture/project1/tags/0.3-bugfix/something.txt
src/tha/tagfinder/tests/fixture/project1/tags/reinout-fixed/something.txt
src/tha/tagfinder/tests/fixture/project1/trunk/something.txt
src/tha/tagfinder/tests/fixture/project2/README.txt
src/tha/tagfinder/tests/fixture/sandbox/reinout/omit_test.txt
src/tha/tagfinder/tests/fixture/sandbox/reinout/reinout_project/tags/1.0/something.txt
src/tha/tagfinder/tests/fixture/sandbox/reinout/reinout_project/tags/1.1/something.txt
src/tha/tagfinder/tests/fixture/sandbox/reinout/reinout_project/trunk/setup.py